{
  "version": "1.0.0",
  "name": "Peera Default",
  "description": "Standard layout for all new tenants",
  "layout": {
    "nav": {
      "items": [
        { "id": "nav.home", "label": "Home" },
        { "id": "nav.status", "label": "Status" },
        { "id": "nav.billing", "label": "Billing" },
        { "id": "nav.docs", "label": "Documents" },
        { "id": "nav.profile", "label": "Profile" },
        { "id": "nav.security", "label": "Security" },
        { "id": "nav.signout", "label": "Sign Out" }
      ]
    },
    "signout": {
      "html": "",
      "script": "clear auth"
    },
    "dashboard": [
      { "id": "summary", "type": "section", "title": "Overview" },
      { "id": "invoices", "type": "section", "title": "Recent Invoices" }
    ]
  },
  "theme": {
    "tokens": {
      "colors": {
        "brand-500": "#465fff",
        "stone-950": "#0c0c0c"
      }
    }
  }
}